setup.py
examplepip26.egg-info/PKG-INFO
examplepip26.egg-info/SOURCES.txt
examplepip26.egg-info/dependency_links.txt
examplepip26.egg-info/top_level.txt
nameof/__init__.py