Metadata-Version: 1.0
Name: examplepip26
Version: 0.0.0
Summary: example
Home-page: UNKNOWN
Author: UNKNOWN
Author-email: UNKNOWN
License: UNKNOWN
Platform: UNKNOWN
